server/__init__.py
server/server.py
server/common/__init__.py
server/common/decos.py
server/common/descryptors.py
server/common/errors.py
server/common/metaclasses.py
server/common/utils.py
server/common/variables.py
server/doc/__init__.py
server/doc/source/__init__.py
server/doc/source/conf.py
server/logs/__init__.py
server/logs/config_client_log.py
server/logs/config_server_log.py
server/server/__init__.py
server/server/add_user.py
server/server/config_window.py
server/server/core.py
server/server/database.py
server/server/main_window.py
server/server/remove_user.py
server/server/stat_window.py
server/unit_tests/__init__.py
Fo4doG_mess_server-0.0.2.dist-info/METADATA
Fo4doG_mess_server-0.0.2.dist-info/WHEEL
Fo4doG_mess_server-0.0.2.dist-info/top_level.txt
Fo4doG_mess_server-0.0.2.dist-info/RECORD
