Metadata-Version: 2.1
Name: Fo4doG-mess-server
Version: 0.0.2
Summary: Fo4doG_mess_server
Home-page: UNKNOWN
Author: Ivan Ivanov
Author-email: iv.iv@yandex.ru
License: UNKNOWN
Platform: UNKNOWN
Requires-Dist: PyQt5
Requires-Dist: sqlalchemy
Requires-Dist: pycryptodome
Requires-Dist: pycryptodomex
